htsql_excel/__init__.py
htsql_excel-0.1.1.dist-info/DESCRIPTION.rst
htsql_excel-0.1.1.dist-info/METADATA
htsql_excel-0.1.1.dist-info/RECORD
htsql_excel-0.1.1.dist-info/WHEEL
htsql_excel-0.1.1.dist-info/entry_points.txt
htsql_excel-0.1.1.dist-info/metadata.json
htsql_excel-0.1.1.dist-info/top_level.txt
htsql_excel-0.1.1.dist-info/zip-safe
