Metadata-Version: 2.0
Name: htsql-excel
Version: 0.1.1
Summary: An HTSQL extension that adds basic Excel support.
Home-page: https://bitbucket.org/prometheus/htsql_excel
Author: Prometheus Research, LLC
Author-email: contact@prometheusresearch.com
License: AGPLv3
Keywords: htsql extension excel xls xlsx
Platform: UNKNOWN
Classifier: Programming Language :: Python :: 2.7
Classifier: License :: OSI Approved :: GNU Affero General Public License v3
Requires-Dist: HTSQL (<3,>=2.3)
Requires-Dist: openpyxl (<3,>=2)
Requires-Dist: xlwt (>=1,<2)
